{
  "last_updated": "2025-08-18T00:00:06.821621",
  "total_stocks": 5,
  "data": [
    {
      "symbol": "AAPL",
      "rs_rank": 95,
      "avg_volume": "89.2M",
      "raw_volume": 89200000
    },
    {
      "symbol": "MSFT",
      "rs_rank": 88,
      "avg_volume": "42.1M",
      "raw_volume": 42100000
    },
    {
      "symbol": "GOOGL",
      "rs_rank": 76,
      "avg_volume": "28.5M",
      "raw_volume": 28500000
    },
    {
      "symbol": "AMZN",
      "rs_rank": 82,
      "avg_volume": "35.7M",
      "raw_volume": 35700000
    },
    {
      "symbol": "TSLA",
      "rs_rank": 91,
      "avg_volume": "91.3M",
      "raw_volume": 91300000
    }
  ]
}